AMOFMS/CGForceFieldParameters.py
AMOFMS/CGPropertiesFromFGSimulation.py
AMOFMS/FGMappingToCG.py
AMOFMS/ObjectiveFunction.py
AMOFMS/Optimization.py
AMOFMS/__init__.py
AMOFMS/DSGPM_TP_MARTINI2/CGPredictionFromDSGPM_TP.py
AMOFMS/DSGPM_TP_MARTINI2/__init__.py
AMOFMS/DSGPM_TP_MARTINI2/average_model_parameters.py
AMOFMS/DSGPM_TP_MARTINI2/inference.py
AMOFMS/DSGPM_TP_MARTINI2/option.py
AMOFMS/DSGPM_TP_MARTINI2/sup_train.py
AMOFMS/DSGPM_TP_MARTINI2/train.py
AMOFMS/DSGPM_TP_MARTINI2/vis.py
AMOFMS/DSGPM_TP_MARTINI2/dataset/__init__.py
AMOFMS/DSGPM_TP_MARTINI2/dataset/collate.py
AMOFMS/DSGPM_TP_MARTINI2/dataset/ham.py
AMOFMS/DSGPM_TP_MARTINI2/dataset/ham_per_file.py
AMOFMS/DSGPM_TP_MARTINI2/model/__init__.py
AMOFMS/DSGPM_TP_MARTINI2/model/best_epoch.pth
AMOFMS/DSGPM_TP_MARTINI2/model/graph_cuts.py
AMOFMS/DSGPM_TP_MARTINI2/model/losses.py
AMOFMS/DSGPM_TP_MARTINI2/model/networks.py
AMOFMS/DSGPM_TP_MARTINI2/utils/__init__.py
AMOFMS/DSGPM_TP_MARTINI2/utils/automorphism_group.py
AMOFMS/DSGPM_TP_MARTINI2/utils/post_processing.py
AMOFMS/DSGPM_TP_MARTINI2/utils/stat.py
AMOFMS/DSGPM_TP_MARTINI2/utils/transforms.py
AMOFMS/DSGPM_TP_MARTINI2/utils/util.py
AMOFMS/tools/__init__.py
AMOFMS/tools/gromacs.py
AMOFMS/tools/lj_query.py
AMOFMS/tools/math_tools.py
AMOFMS/tools/properties.py
AMOFMS/tools/top_item.py
AMOFMS/tools/utilies.py
AMOFMS/tools/force_field/__init__.py
AMOFMS/tools/force_field/martini_v2.2.itp
AMOFMS/tools/force_field/martini_v2.3P.itp
AMOFMS/tools/force_field/martini_v3.0.0.itp
AMOFMS/tools/force_field/spica_protein_v2.prm
AMOFMS-1.0.dist-info/LICENSE
AMOFMS-1.0.dist-info/METADATA
AMOFMS-1.0.dist-info/WHEEL
AMOFMS-1.0.dist-info/entry_points.txt
AMOFMS-1.0.dist-info/top_level.txt
AMOFMS-1.0.dist-info/RECORD
