Metadata-Version: 2.1
Name: AMOFMS
Version: 1.0
Summary: AMOFMS: An Automated Mapping and Optimization Framework for Multiscale Simulation
Home-page: https://github.com/JiangGroup/AMOFMS
Author: Zhixuan Zhong
Author-email: zhixuan@iccas.ac.cn
License: MIT
Classifier: Programming Language :: Python
Classifier: License :: OSI Approved :: MIT License
Classifier: Operating System :: OS Independent
Requires-Python: >=3.9
License-File: LICENSE
Requires-Dist: lipyphilic ==0.10.0
Requires-Dist: matplotlib ==3.4.3
Requires-Dist: MDAnalysis ==2.7.0
Requires-Dist: networkx ==3.2
Requires-Dist: numpy ==1.22.3
Requires-Dist: pexpect ==4.9.0
Requires-Dist: Pillow ==10.2.0
Requires-Dist: pyswarms ==1.3.0
Requires-Dist: rdkit ==2023.9.4
Requires-Dist: Requests ==2.31.0
Requires-Dist: scikit-learn ==1.3.2
Requires-Dist: scipy ==1.8.1
Requires-Dist: seaborn ==0.13.2
Requires-Dist: scikit-image
Requires-Dist: torch ==2.1.2
Requires-Dist: torch-geometric ==2.4.0
Requires-Dist: tqdm ==4.66.1
Requires-Dist: tensorboard
